License.txt
README.md
setup.cfg
setup.py
pythmath/__init__.py
pythmath/errors.py
pythmath/fractions.py
pythmath/geometry.py
pythmath/lines.py
pythmath/math.py
pythmath/sales.py
pythmath/statistics.py
pythmath.egg-info/PKG-INFO
pythmath.egg-info/SOURCES.txt
pythmath.egg-info/dependency_links.txt
pythmath.egg-info/top_level.txt