Metadata-Version: 2.1
Name: pythmath
Version: 0.2.5
Summary: Pure Mathematics library which performs basic math operations such as sin, cos, tan and it also includes basic statistical functions such as mean, median mode etc.,
Home-page: https://github.com/roshaan55/pycamdetector
Download-URL: https://github.com/roshaan55/pycamdetector/archive/refs/tags/v_0.6.5.tar.gz
Author: Roshaan Mehmood
Author-email: roshaan55@gmail.com
License: MIT
Keywords: pythmath,mathlibrary,sine,area of triangle,area of circle,area of square
Classifier: Development Status :: 3 - Alpha
Classifier: Intended Audience :: Developers
Classifier: Topic :: Software Development :: Build Tools
Classifier: License :: OSI Approved :: MIT License
Classifier: Programming Language :: Python :: 3.6
Classifier: Programming Language :: Python :: 3.7
Classifier: Programming Language :: Python :: 3.8
Classifier: Programming Language :: Python :: 3.9
License-File: License.txt
